{"name":"filter to edit","id":"opencart;filter-to-edit","testSteps":[{"number":1,"description":"Example: {username\u003ddemo, password\u003ddemo, seourl\u003dSEO URL, query\u003dproduct_id\u003d47, keyword\u003dhp-lp3065, store\u003dDefault, language\u003dEnglish, queryedit\u003dcategory_id\u003d18, keywordedit\u003dNO, warning\u003dWarning}","duration":23368,"startTime":"2022-05-04T11:16:33.219-05:00[America/Bogota]","screenshots":[{"screenshot":"63607af9970f762b267bec7134843d561b69907a90d7d4ae8299d5598cafb28d.png","timeStamp":1651681016587}],"result":"SUCCESS","precondition":false,"level":0,"lineNumber":0,"children":[{"number":2,"description":"Given Tania wants to edit data from the list consulted in SEO URL","duration":5717,"startTime":"2022-05-04T11:16:33.260-05:00[America/Bogota]","screenshots":[{"screenshot":"d37066bf1aaad08ffc5fb6a6553acdaf3b47185302102113056f7a6c90ae0119.png","timeStamp":1651680998977}],"result":"SUCCESS","precondition":false,"level":1,"lineNumber":0,"children":[{"number":3,"description":"Tania ruiz sanchez open up","duration":5216,"startTime":"2022-05-04T11:16:33.758-05:00[America/Bogota]","screenshots":[{"screenshot":"d37066bf1aaad08ffc5fb6a6553acdaf3b47185302102113056f7a6c90ae0119.png","timeStamp":1651680998969}],"result":"SUCCESS","precondition":false,"level":2,"lineNumber":0,"children":[{"number":4,"description":"Tania Ruiz Sanchez opens the Cart open page","duration":5179,"startTime":"2022-05-04T11:16:33.779-05:00[America/Bogota]","screenshots":[{"screenshot":"d37066bf1aaad08ffc5fb6a6553acdaf3b47185302102113056f7a6c90ae0119.png","timeStamp":1651680998958}],"result":"SUCCESS","precondition":false,"level":3,"lineNumber":0}]}]},{"number":5,"description":"When She enters the data she wants to edit\r\n| username | password | seourl | query | keyword | store | language | queryedit | keywordedit |\r\n| demo | demo | SEO URL | product_id\u003d47 | hp-lp3065 | Default | English | category_id\u003d18 | NO |","duration":17114,"startTime":"2022-05-04T11:16:38.984-05:00[America/Bogota]","screenshots":[{"screenshot":"63607af9970f762b267bec7134843d561b69907a90d7d4ae8299d5598cafb28d.png","timeStamp":1651681016090}],"result":"SUCCESS","precondition":false,"level":1,"lineNumber":0,"children":[{"number":6,"description":"Tania ruiz sanchez filter edit","duration":17073,"startTime":"2022-05-04T11:16:39.005-05:00[America/Bogota]","screenshots":[{"screenshot":"63607af9970f762b267bec7134843d561b69907a90d7d4ae8299d5598cafb28d.png","timeStamp":1651681016078}],"result":"SUCCESS","precondition":false,"level":2,"lineNumber":0,"children":[{"number":7,"description":"Tania Ruiz Sanchez enters \u0027demo\u0027 into enter username","duration":608,"startTime":"2022-05-04T11:16:39.018-05:00[America/Bogota]","screenshots":[{"screenshot":"6ae890b09f600b09ccfe564a471155458cde7dc68daf6db742ad7312d2204e35.png","timeStamp":1651680999626}],"result":"SUCCESS","precondition":false,"level":3,"lineNumber":0},{"number":8,"description":"Tania Ruiz Sanchez enters \u0027demo\u0027 into enter password","duration":627,"startTime":"2022-05-04T11:16:39.642-05:00[America/Bogota]","screenshots":[{"screenshot":"46ed8f92daed19dfd4e0b377e8e883d0f50bcac41b2ab1f9111a7e5233249d3e.png","timeStamp":1651681000266}],"result":"SUCCESS","precondition":false,"level":3,"lineNumber":0},{"number":9,"description":"Tania Ruiz Sanchez clicks on Click on the login button","duration":2374,"startTime":"2022-05-04T11:16:40.276-05:00[America/Bogota]","screenshots":[{"screenshot":"4aefc314b77357540978005cd1334d4131a71be7d9cb2d2450edaf71ac4867cd.png","timeStamp":1651681002650}],"result":"SUCCESS","precondition":false,"level":3,"lineNumber":0},{"number":10,"description":"Tania Ruiz Sanchez clicks on Click on Desing","duration":578,"startTime":"2022-05-04T11:16:42.656-05:00[America/Bogota]","screenshots":[{"screenshot":"cde3d0f4a887c35c7569c0beb2ffe2f5f943f6bfb5f93e49fa1806e7e94527a8.png","timeStamp":1651681003234}],"result":"SUCCESS","precondition":false,"level":3,"lineNumber":0},{"number":11,"description":"Tania Ruiz Sanchez clicks on Select SEO URL","duration":826,"startTime":"2022-05-04T11:16:43.238-05:00[America/Bogota]","screenshots":[{"screenshot":"c98d4c50ed027ac61260a559638bfb93b105439ef750044841fb75d2f188cb2f.png","timeStamp":1651681004064}],"result":"SUCCESS","precondition":false,"level":3,"lineNumber":0},{"number":12,"description":"Tania Ruiz Sanchez enters \u0027product_id\u003d47\u0027 into Write the query","duration":549,"startTime":"2022-05-04T11:16:44.073-05:00[America/Bogota]","screenshots":[{"screenshot":"75093f4f10c86fb05bf6d8421fd0b6f127712d9731aa2d0b17fd4837452cf214.png","timeStamp":1651681004622}],"result":"SUCCESS","precondition":false,"level":3,"lineNumber":0},{"number":13,"description":"Tania Ruiz Sanchez enters \u0027hp-lp3065\u0027 into Write the keyword","duration":459,"startTime":"2022-05-04T11:16:44.630-05:00[America/Bogota]","screenshots":[{"screenshot":"521a050a71767dd4c2c6c4c721ff8ee462bb97c07df775f6bb38002d5cc8c13c.png","timeStamp":1651681005089}],"result":"SUCCESS","precondition":false,"level":3,"lineNumber":0},{"number":14,"description":"Tania Ruiz Sanchez clicks on Click Store","duration":476,"startTime":"2022-05-04T11:16:45.098-05:00[America/Bogota]","screenshots":[{"screenshot":"36e2ee5ac82f5fd1af57c81db4b1c02f9a9a5bd66852167c132ee6704cb065f0.png","timeStamp":1651681005574}],"result":"SUCCESS","precondition":false,"level":3,"lineNumber":0},{"number":15,"description":"Tania Ruiz Sanchez types \u0027ARROW_DOWN\u0027 in Click Store","duration":323,"startTime":"2022-05-04T11:16:45.595-05:00[America/Bogota]","screenshots":[{"screenshot":"4b88942fb74009f65d714d6e47f946c8e08e60a61a1f54543960e933118c0a16.png","timeStamp":1651681005918}],"result":"SUCCESS","precondition":false,"level":3,"lineNumber":0},{"number":16,"description":"Tania Ruiz Sanchez types \u0027ARROW_DOWN\u0027 in Click Store","duration":299,"startTime":"2022-05-04T11:16:45.930-05:00[America/Bogota]","screenshots":[{"screenshot":"4b88942fb74009f65d714d6e47f946c8e08e60a61a1f54543960e933118c0a16.png","timeStamp":1651681006229}],"result":"SUCCESS","precondition":false,"level":3,"lineNumber":0},{"number":17,"description":"Tania Ruiz Sanchez types \u0027ENTER\u0027 in Click Store","duration":285,"startTime":"2022-05-04T11:16:46.244-05:00[America/Bogota]","screenshots":[{"screenshot":"53f133b0692243a542d1ede3cdbbc6d32ff7edb550149f7be914d19c952c67ed.png","timeStamp":1651681006529}],"result":"SUCCESS","precondition":false,"level":3,"lineNumber":0},{"number":18,"description":"Tania Ruiz Sanchez clicks on Click Languaje","duration":706,"startTime":"2022-05-04T11:16:46.541-05:00[America/Bogota]","screenshots":[{"screenshot":"b82ba75d9f2cbe05851666ca2d94037db6f4daaad9278f428eed0cb626941dc1.png","timeStamp":1651681007247}],"result":"SUCCESS","precondition":false,"level":3,"lineNumber":0},{"number":19,"description":"Tania Ruiz Sanchez types \u0027ARROW_DOWN\u0027 in Click Languaje","duration":323,"startTime":"2022-05-04T11:16:47.255-05:00[America/Bogota]","screenshots":[{"screenshot":"a3a6555b68f4644b5b9f336a7042a6f23d0a3ec26c08bca044b593c8d4b47b82.png","timeStamp":1651681007578}],"result":"SUCCESS","precondition":false,"level":3,"lineNumber":0},{"number":20,"description":"Tania Ruiz Sanchez types \u0027ARROW_DOWN\u0027 in Click Languaje","duration":276,"startTime":"2022-05-04T11:16:47.585-05:00[America/Bogota]","screenshots":[{"screenshot":"a3a6555b68f4644b5b9f336a7042a6f23d0a3ec26c08bca044b593c8d4b47b82.png","timeStamp":1651681007861}],"result":"SUCCESS","precondition":false,"level":3,"lineNumber":0},{"number":21,"description":"Tania Ruiz Sanchez types \u0027ENTER\u0027 in Click Languaje","duration":265,"startTime":"2022-05-04T11:16:47.880-05:00[America/Bogota]","screenshots":[{"screenshot":"a3a6555b68f4644b5b9f336a7042a6f23d0a3ec26c08bca044b593c8d4b47b82.png","timeStamp":1651681008145}],"result":"SUCCESS","precondition":false,"level":3,"lineNumber":0},{"number":22,"description":"Tania Ruiz Sanchez clicks on Click boton Filter","duration":1077,"startTime":"2022-05-04T11:16:48.154-05:00[America/Bogota]","screenshots":[{"screenshot":"2da896447bcf33ce6fffe30ce75c41d162b2ff7da85e78b5b722cb72d52c8a0a.png","timeStamp":1651681009231}],"result":"SUCCESS","precondition":false,"level":3,"lineNumber":0},{"number":23,"description":"Tania Ruiz Sanchez clicks on Click boton edit","duration":611,"startTime":"2022-05-04T11:16:49.237-05:00[America/Bogota]","screenshots":[{"screenshot":"cff638ccaa43502b144671bfcd05445b5f9a496625aa1e8c01e36d39a776913a.png","timeStamp":1651681009848}],"result":"SUCCESS","precondition":false,"level":3,"lineNumber":0},{"number":24,"description":"Tania Ruiz Sanchez clicks on Click boton edit","duration":1057,"startTime":"2022-05-04T11:16:49.864-05:00[America/Bogota]","screenshots":[{"screenshot":"71a3d991506244cb61e037141fc7d3cefe29947ef886126c07ce884e875900c7.png","timeStamp":1651681010921}],"result":"SUCCESS","precondition":false,"level":3,"lineNumber":0},{"number":25,"description":"Tania Ruiz Sanchez enters \u0027category_id\u003d18\u0027 into Write the query edit","duration":696,"startTime":"2022-05-04T11:16:50.938-05:00[America/Bogota]","screenshots":[{"screenshot":"80b8ebb2cc10e2389d2c01ec7449fa29ac70f14560d9786117f0224335395f61.png","timeStamp":1651681011634}],"result":"SUCCESS","precondition":false,"level":3,"lineNumber":0},{"number":26,"description":"Tania Ruiz Sanchez enters \u0027NO\u0027 into Write the keyword edit","duration":722,"startTime":"2022-05-04T11:16:51.650-05:00[America/Bogota]","screenshots":[{"screenshot":"5c8f0fb0af75a99fb3b7292917a43c898477d31803698fcb9ab1ef0624361020.png","timeStamp":1651681012372}],"result":"SUCCESS","precondition":false,"level":3,"lineNumber":0},{"number":27,"description":"Tania Ruiz Sanchez clicks on Select the Store edit","duration":698,"startTime":"2022-05-04T11:16:52.381-05:00[America/Bogota]","screenshots":[{"screenshot":"46727b95c4b4e5194b595652c299ec7f59c4c170100f48df4aae02465cafb559.png","timeStamp":1651681013079}],"result":"SUCCESS","precondition":false,"level":3,"lineNumber":0},{"number":28,"description":"Tania Ruiz Sanchez types \u0027ARROW_DOWN\u0027 in Select the Store edit","duration":313,"startTime":"2022-05-04T11:16:53.096-05:00[America/Bogota]","screenshots":[{"screenshot":"43ba284d9fa65a46fd41983adf40dec9216b27a13ce136eb7914cdec4faa25f5.png","timeStamp":1651681013409}],"result":"SUCCESS","precondition":false,"level":3,"lineNumber":0},{"number":29,"description":"Tania Ruiz Sanchez types \u0027ENTER\u0027 in Select the Store edit","duration":261,"startTime":"2022-05-04T11:16:53.427-05:00[America/Bogota]","screenshots":[{"screenshot":"3123243825952db4ee84a5f26d37548b6d364b292fa2e9c4138e87bcdb88e635.png","timeStamp":1651681013688}],"result":"SUCCESS","precondition":false,"level":3,"lineNumber":0},{"number":30,"description":"Tania Ruiz Sanchez clicks on Select the Languaje edit","duration":635,"startTime":"2022-05-04T11:16:53.697-05:00[America/Bogota]","screenshots":[{"screenshot":"23a6a5295028c451319820de805138146ff67d6a07c6e2955a41634e9fab46c1.png","timeStamp":1651681014332}],"result":"SUCCESS","precondition":false,"level":3,"lineNumber":0},{"number":31,"description":"Tania Ruiz Sanchez types \u0027ARROW_DOWN\u0027 in Select the Languaje edit","duration":295,"startTime":"2022-05-04T11:16:54.338-05:00[America/Bogota]","screenshots":[{"screenshot":"05d5411f9b8dff0ac12bdef70d762cb38a8920dee0d7ad064a773c4f2ecff5a1.png","timeStamp":1651681014633}],"result":"SUCCESS","precondition":false,"level":3,"lineNumber":0},{"number":32,"description":"Tania Ruiz Sanchez types \u0027ENTER\u0027 in Select the Languaje edit","duration":277,"startTime":"2022-05-04T11:16:54.642-05:00[America/Bogota]","screenshots":[{"screenshot":"d0ca050dcd154cb7e9bf0396069eed5696e5043f0f8a121a9a648fbcb12f0f7a.png","timeStamp":1651681014919}],"result":"SUCCESS","precondition":false,"level":3,"lineNumber":0},{"number":33,"description":"Tania Ruiz Sanchez clicks on Click boton Save","duration":1117,"startTime":"2022-05-04T11:16:54.929-05:00[America/Bogota]","screenshots":[{"screenshot":"63607af9970f762b267bec7134843d561b69907a90d7d4ae8299d5598cafb28d.png","timeStamp":1651681016046}],"result":"SUCCESS","precondition":false,"level":3,"lineNumber":0}]}]},{"number":34,"description":"Then She displays a warning message\r\n| warning |\r\n| Warning |","duration":473,"startTime":"2022-05-04T11:16:56.098-05:00[America/Bogota]","screenshots":[{"screenshot":"63607af9970f762b267bec7134843d561b69907a90d7d4ae8299d5598cafb28d.png","timeStamp":1651681016571}],"result":"SUCCESS","precondition":false,"level":1,"lineNumber":0,"children":[{"number":35,"description":"Then answer edit","duration":273,"startTime":"2022-05-04T11:16:56.270-05:00[America/Bogota]","screenshots":[{"screenshot":"63607af9970f762b267bec7134843d561b69907a90d7d4ae8299d5598cafb28d.png","timeStamp":1651681016543}],"result":"SUCCESS","precondition":false,"level":2,"lineNumber":0}]}]}],"userStory":{"id":"opencart","storyName":"openCart","path":"src/test/resources/features/openCart.feature","narrative":"  As a user I want to filter the different data of the SEO URL list","type":"feature"},"featureTag":{"name":"Features/openCart","type":"feature","displayName":"Features/openCart"},"title":"filter to edit","tags":[{"name":"scenario2","type":"tag","displayName":"scenario2"},{"name":"openCart","type":"feature","displayName":"openCart"},{"name":"stories","type":"tag","displayName":"stories"}],"startTime":"2022-05-04T11:16:33.118-05:00[America/Bogota]","duration":24138,"projectKey":"","isManualTestingUpToDate":false,"dataTable":{"headers":["username","password","seourl","query","keyword","store","language","queryedit","keywordedit","warning"],"rows":[{"values":["demo","demo","SEO URL","product_id\u003d47","hp-lp3065","Default","English","category_id\u003d18","NO","Warning"],"lineNumber":37,"result":"SUCCESS"}],"predefinedRows":true,"scenarioOutline":"Given Tania wants to edit data from the list consulted in SEO URL\n\rWhen She enters the data she wants to edit\n\rThen She displays a warning message\n\r","dataSetDescriptors":[{"startRow":0,"rowCount":0,"name":""}],"lineNumbersForEachRow":{"0":37}},"manual":false,"testSource":"Cucumber","actors":[{"name":"Tania Ruiz Sanchez","can":["browse the web"]}],"result":"SUCCESS","scenarioOutline":"Given Tania wants to edit data from the list consulted in SEO URL\r\nWhen She enters the data she wants to edit\r\n|username | password | seourl | query | keyword | store | language | queryedit | keywordedit|\r\n|\u003cusername\u003e | \u003cpassword\u003e | \u003cseourl\u003e | \u003cquery\u003e | \u003ckeyword\u003e | \u003cstore\u003e | \u003clanguage\u003e | \u003cqueryedit\u003e | \u003ckeywordedit\u003e|\r\nThen She displays a warning message\r\n|warning|\r\n|\u003cwarning\u003e|"}